{
  "schema_version": 2,
  "product": "Automation",
  "slug": "automation",
  "picker_testid": "automation-picker-item",
  "module_testid": "automation-module",
  "category": null,
  "learned_at": "2026-06-12T16:15:44.236844+00:00",
  "fields": [
    {
      "aria_label": "product-name",
      "clean_name": "displayName",
      "control": "text",
      "data_name_override": null,
      "data_testid": null,
      "id": null,
      "label": "product-name",
      "name": "displayName",
      "options": null,
      "placeholder": "Automation",
      "selector": "input[aria-label=\"product-name\"][name=\"displayName\"]",
      "selector_unique": true,
      "signature": "input|text|displayName|product-name|||Automation|",
      "tag": "input",
      "type": "text",
      "value": "",
      "visible": true,
      "revealed_by": null
    },
    {
      "aria_label": "Region",
      "clean_name": "region",
      "control": "select",
      "data_name_override": null,
      "data_testid": null,
      "id": null,
      "label": "Region",
      "name": "region",
      "options": [
        {
          "group": "United States",
          "text": "Central US",
          "value": "us-central"
        },
        {
          "group": "United States",
          "text": "East US",
          "value": "us-east"
        },
        {
          "group": "United States",
          "text": "East US 2",
          "value": "us-east-2"
        },
        {
          "group": "United States",
          "text": "North Central US",
          "value": "us-north-central"
        },
        {
          "group": "United States",
          "text": "South Central US",
          "value": "us-south-central"
        },
        {
          "group": "United States",
          "text": "West Central US",
          "value": "us-west-central"
        },
        {
          "group": "United States",
          "text": "West US",
          "value": "us-west"
        },
        {
          "group": "United States",
          "text": "West US 2",
          "value": "us-west-2"
        },
        {
          "group": "United States",
          "text": "West US 3",
          "value": "us-west-3"
        },
        {
          "group": "United Kingdom",
          "text": "UK South",
          "value": "united-kingdom-south"
        },
        {
          "group": "United Kingdom",
          "text": "UK West",
          "value": "united-kingdom-west"
        },
        {
          "group": "United Arab Emirates",
          "text": "UAE Central",
          "value": "uae-central"
        },
        {
          "group": "United Arab Emirates",
          "text": "UAE North",
          "value": "uae-north"
        },
        {
          "group": "Switzerland",
          "text": "Switzerland North",
          "value": "switzerland-north"
        },
        {
          "group": "Switzerland",
          "text": "Switzerland West",
          "value": "switzerland-west"
        },
        {
          "group": "Sweden",
          "text": "Sweden Central",
          "value": "sweden-central"
        },
        {
          "group": "Sweden",
          "text": "Sweden South",
          "value": "sweden-south"
        },
        {
          "group": "Spain",
          "text": "Spain Central",
          "value": "spain-central"
        },
        {
          "group": "Qatar",
          "text": "Qatar Central",
          "value": "qatar-central"
        },
        {
          "group": "Poland",
          "text": "Poland Central",
          "value": "poland-central"
        },
        {
          "group": "Norway",
          "text": "Norway East",
          "value": "norway-east"
        },
        {
          "group": "Norway",
          "text": "Norway West",
          "value": "norway-west"
        },
        {
          "group": "Mexico",
          "text": "Mexico Central",
          "value": "mexico-central"
        },
        {
          "group": "Korea",
          "text": "Korea Central",
          "value": "korea-central"
        },
        {
          "group": "Korea",
          "text": "Korea South",
          "value": "korea-south"
        },
        {
          "group": "Japan",
          "text": "Japan East",
          "value": "japan-east"
        },
        {
          "group": "Japan",
          "text": "Japan West",
          "value": "japan-west"
        },
        {
          "group": "Italy",
          "text": "Italy North",
          "value": "italy-north"
        },
        {
          "group": "Israel",
          "text": "Israel Central",
          "value": "israel-central"
        },
        {
          "group": "India",
          "text": "Central India",
          "value": "central-india"
        },
        {
          "group": "India",
          "text": "South India",
          "value": "south-india"
        },
        {
          "group": "Germany",
          "text": "Germany North",
          "value": "germany-north"
        },
        {
          "group": "Germany",
          "text": "Germany West Central",
          "value": "germany-west-central"
        },
        {
          "group": "France",
          "text": "France Central",
          "value": "france-central"
        },
        {
          "group": "France",
          "text": "France South",
          "value": "france-south"
        },
        {
          "group": "Europe",
          "text": "North Europe",
          "value": "europe-north"
        },
        {
          "group": "Europe",
          "text": "West Europe",
          "value": "europe-west"
        },
        {
          "group": "Canada",
          "text": "Canada Central",
          "value": "canada-central"
        },
        {
          "group": "Canada",
          "text": "Canada East",
          "value": "canada-east"
        },
        {
          "group": "Brazil",
          "text": "Brazil South",
          "value": "brazil-south"
        },
        {
          "group": "Brazil",
          "text": "Brazil Southeast",
          "value": "brazil-southeast"
        },
        {
          "group": "Azure Government",
          "text": "US Gov Arizona",
          "value": "usgov-arizona"
        },
        {
          "group": "Azure Government",
          "text": "US Gov Texas",
          "value": "usgov-texas"
        },
        {
          "group": "Azure Government",
          "text": "US Gov Virginia",
          "value": "usgov-virginia"
        },
        {
          "group": "Australia",
          "text": "Australia Central",
          "value": "australia-central"
        },
        {
          "group": "Australia",
          "text": "Australia Central 2",
          "value": "australia-central-2"
        },
        {
          "group": "Australia",
          "text": "Australia East",
          "value": "australia-east"
        },
        {
          "group": "Australia",
          "text": "Australia Southeast",
          "value": "australia-southeast"
        },
        {
          "group": "Asia Pacific",
          "text": "East Asia",
          "value": "asia-pacific-east"
        },
        {
          "group": "Asia Pacific",
          "text": "Southeast Asia",
          "value": "asia-pacific-southeast"
        },
        {
          "group": "Africa",
          "text": "South Africa North",
          "value": "south-africa-north"
        },
        {
          "group": "Africa",
          "text": "South Africa West",
          "value": "south-africa-west"
        }
      ],
      "placeholder": null,
      "selector": "select[aria-label=\"Region\"][name=\"region\"]",
      "selector_unique": true,
      "signature": "select||region|Region||||",
      "tag": "select",
      "type": null,
      "value": "us-east-2",
      "visible": true,
      "revealed_by": null
    },
    {
      "aria_label": "Capability",
      "clean_name": "capability",
      "control": "select",
      "data_name_override": null,
      "data_testid": null,
      "id": null,
      "label": "Capability",
      "name": "capability",
      "options": [
        {
          "group": null,
          "text": "Configuration Management (Azure nodes)",
          "value": "azure-configuration-management"
        },
        {
          "group": null,
          "text": "Configuration Management (non-Azure nodes)",
          "value": "configuration-management"
        },
        {
          "group": null,
          "text": "Process Automation",
          "value": "process-automation"
        },
        {
          "group": null,
          "text": "Update Management (Azure and non-Azure nodes)",
          "value": "update-management"
        }
      ],
      "placeholder": null,
      "selector": "select[aria-label=\"Capability\"][name=\"capability\"]",
      "selector_unique": true,
      "signature": "select||capability|Capability||||",
      "tag": "select",
      "type": null,
      "value": "update-management",
      "visible": true,
      "revealed_by": null
    },
    {
      "aria_label": "Nodes",
      "clean_name": "updateManagmentNodes",
      "control": "number",
      "data_name_override": null,
      "data_testid": null,
      "id": null,
      "label": "Nodes",
      "name": "updateManagmentNodes",
      "options": null,
      "placeholder": null,
      "selector": "input[aria-label=\"Nodes\"][name=\"updateManagmentNodes\"]",
      "selector_unique": true,
      "signature": "input|number|updateManagmentNodes|Nodes||||",
      "tag": "input",
      "type": "number",
      "value": "5",
      "visible": true,
      "revealed_by": null,
      "selector_variants": [
        {
          "when": {
            "field": "capability",
            "value": "azure-configuration-management",
            "text": "Configuration Management (Azure nodes)"
          },
          "selector": "input[aria-label=\"Nodes\"][name=\"azureConfigurationNodes\"]",
          "name": "azureConfigurationNodes",
          "options": null
        }
      ],
      "depends_on": [
        "capability"
      ]
    },
    {
      "aria_label": "Additional nodes",
      "clean_name": "nonAzureConfigurationNodes",
      "control": "number",
      "data_name_override": null,
      "data_testid": null,
      "id": null,
      "label": "Additional nodes",
      "name": "nonAzureConfigurationNodes",
      "options": null,
      "placeholder": null,
      "selector": "input[aria-label=\"Additional\\ nodes\"][name=\"nonAzureConfigurationNodes\"]",
      "selector_unique": true,
      "signature": "input|number|nonAzureConfigurationNodes|Additional nodes||||",
      "tag": "input",
      "type": "number",
      "value": "0",
      "visible": true,
      "revealed_by": null,
      "present_when": [
        {
          "field": "capability",
          "value": "configuration-management",
          "text": "Configuration Management (non-Azure nodes)"
        }
      ],
      "depends_on": [
        "capability"
      ]
    },
    {
      "aria_label": "Additional minutes",
      "clean_name": "processMinutes",
      "control": "number",
      "data_name_override": null,
      "data_testid": null,
      "id": null,
      "label": "Additional minutes",
      "name": "processMinutes",
      "options": null,
      "placeholder": null,
      "selector": "input[aria-label=\"Additional\\ minutes\"][name=\"processMinutes\"]",
      "selector_unique": true,
      "signature": "input|number|processMinutes|Additional minutes||||",
      "tag": "input",
      "type": "number",
      "value": "0",
      "visible": true,
      "revealed_by": null,
      "present_when": [
        {
          "field": "capability",
          "value": "process-automation",
          "text": "Process Automation"
        }
      ],
      "depends_on": [
        "capability"
      ]
    },
    {
      "aria_label": "Watchers",
      "clean_name": "watchersCount",
      "control": "number",
      "data_name_override": null,
      "data_testid": null,
      "id": null,
      "label": "Watchers",
      "name": "watchersCount",
      "options": null,
      "placeholder": null,
      "selector": "input[aria-label=\"Watchers\"][name=\"watchersCount\"]",
      "selector_unique": true,
      "signature": "input|number|watchersCount|Watchers||||",
      "tag": "input",
      "type": "number",
      "value": "1",
      "visible": true,
      "revealed_by": null,
      "present_when": [
        {
          "field": "capability",
          "value": "process-automation",
          "text": "Process Automation"
        }
      ],
      "depends_on": [
        "capability"
      ]
    },
    {
      "aria_label": "Hours",
      "clean_name": "watchersHours",
      "control": "number",
      "data_name_override": null,
      "data_testid": null,
      "id": null,
      "label": "Hours",
      "name": "watchersHours",
      "options": null,
      "placeholder": null,
      "selector": "input[aria-label=\"Hours\"][name=\"watchersHours\"]",
      "selector_unique": true,
      "signature": "input|number|watchersHours|Hours||||",
      "tag": "input",
      "type": "number",
      "value": "730",
      "visible": true,
      "revealed_by": null,
      "present_when": [
        {
          "field": "capability",
          "value": "process-automation",
          "text": "Process Automation"
        }
      ],
      "depends_on": [
        "capability"
      ]
    },
    {
      "aria_label": "Hours",
      "clean_name": "watchersHoursFactor",
      "control": "select",
      "data_name_override": null,
      "data_testid": null,
      "id": null,
      "label": "Hours",
      "name": "watchersHoursFactor",
      "options": [
        {
          "group": null,
          "text": "Hours",
          "value": "1"
        },
        {
          "group": null,
          "text": "Days",
          "value": "24"
        },
        {
          "group": null,
          "text": "Month",
          "value": "730"
        }
      ],
      "placeholder": null,
      "selector": "select[aria-label=\"Hours\"][name=\"watchersHoursFactor\"]",
      "selector_unique": true,
      "signature": "select||watchersHoursFactor|Hours||||",
      "tag": "select",
      "type": null,
      "value": "1",
      "visible": true,
      "revealed_by": null,
      "present_when": [
        {
          "field": "capability",
          "value": "process-automation",
          "text": "Process Automation"
        }
      ],
      "depends_on": [
        "capability"
      ]
    }
  ],
  "toggles": []
}